yt_dlp_plugins/__init__.py
yt_dlp_plugins/extractor/__init__.py
yt_dlp_plugins/extractor/ytdlp_51cg.py
yt_dlp_51cg-0.1.0.dist-info/METADATA
yt_dlp_51cg-0.1.0.dist-info/WHEEL
yt_dlp_51cg-0.1.0.dist-info/top_level.txt
yt_dlp_51cg-0.1.0.dist-info/RECORD
