Metadata-Version: 2.4
Name: yt-dlp-51cg
Version: 0.1.0
Summary: Add your description here
Requires-Python: >=3.12
Requires-Dist: playwright>=1.55.0
Requires-Dist: yt-dlp>=2025.10.22
